src/led.v
`timescale 1ns / 1ns
`define T0H     350.0   // 0.35 us
`define T0L     800.0   // 0.8 us
`define T1H     700.0   // 0.7 us
`define T1L     600.0   // 0.6 us
`define MARGIN  150.0   // +/- 150 ns
`define RET     50000.0 // 50 us

module led(
    input           i_serial,
	//input			  clk,
    output          o_serial,
    output [23:0]   o_led);
    //***********************************************************************
    //  Doing "Things"
    //***********************************************************************
    localparam       CLK_PRD  = 50; //Clock period in ns
    localparam [4:0] T0H_MIN  = ((`T0H - `MARGIN)/CLK_PRD);
    localparam [4:0] T0H_MAX  = ((`T0H + `MARGIN)/CLK_PRD);
    localparam [4:0] T1H_MIN  = ((`T1H - `MARGIN)/CLK_PRD);
    localparam [4:0] T1H_MAX  = ((`T1H + `MARGIN)/CLK_PRD);
    localparam [9:0] RST_MIN  = ((`RET)/CLK_PRD);
    //***********************************************************************
    //  Signal Declaration
    //***********************************************************************
    reg [9:0]rst_timer = 0;
    reg [4:0]bit_timer = 0;
    reg [4:0]bit_cntr  = 0;
    reg [1:0]state_reg = 0;
    reg [1:0]state_nxt = 0;
    reg [0:23]data     = 0;
    reg i_serial_tmp   = 0;
    reg i_serial_sync  = 0;
    reg clk            = 0;
    //***********************************************************************
    //  States Declaration
    //***********************************************************************
    localparam[1:0]
    idle    = 2'd0,
    measure = 2'd1,
    check   = 2'd2;
    //***********************************************************************
    //  Clock Simulation
    //***********************************************************************
    always #(CLK_PRD/2) clk = ~clk;
    //***********************************************************************
    //  Input(i_serial) Synchronization
    //***********************************************************************   
    always@(posedge clk) 
    begin
        i_serial_tmp <= i_serial;
        i_serial_sync <= i_serial_tmp;
    end
    //***********************************************************************
    //  State Register, Reset Timer, Bit Timer & Bit Counter
    //***********************************************************************   
    always@(posedge clk) 
    begin
        state_reg <= state_nxt;
        //Things to do in "idle" state
        if (state_reg == idle) begin
            bit_timer <= 0;
            if (~i_serial_sync)         
                rst_timer <= (rst_timer<RST_MIN)?rst_timer+10'd1:RST_MIN;
            else rst_timer  <= 0;
        end
        //Things to do in "measure" state        
        if (state_reg == measure) begin
            bit_timer <= bit_timer+5'd1;
        end
        //Things to do in "check" state
        if (state_reg == check) begin
            bit_cntr <= bit_cntr+5'd1;
            if((bit_timer>=T0H_MIN)&&(bit_timer<=T0H_MAX)) 
            data[bit_cntr] <= 1'd0; else if
            ((bit_timer>=T1H_MIN)&&(bit_timer<=T1H_MAX)) 
            data[bit_cntr] <= 1'd1; else 
            data[bit_cntr] <= 1'd0;
        end
        //Things to do when reset is detected
        if (rst_timer==RST_MIN) begin
            bit_cntr <= 0;
            data <= 0;
        end
    end
    //***********************************************************************
    //  Next State Logic
    //***********************************************************************   
    always@* 
    begin
        state_nxt = state_reg;
        case(state_reg)
            idle: begin
                if(bit_cntr<24)
                if(i_serial_sync) state_nxt = measure;
            end
            measure: begin
                if(~i_serial_sync) state_nxt = check;
            end
            check: begin
                state_nxt = idle;
            end
            default: state_nxt = idle;
        endcase
    end
    //***********************************************************************
    // Output Assignment
    //***********************************************************************   
    assign o_serial = (bit_cntr==24)?i_serial:1'd0;
    assign o_led = (bit_cntr==24)?data:24'd0;
endmodule

tb/sams_tb.v
`timescale 1ns / 1ns
`include "led.v"
`define T0H     350.0   // 0.35 us
`define T0L     800.0   // 0.8 us
`define T1H     700.0   // 0.7 us
`define T1L     600.0   // 0.6 us
`define MARGIN  150.0   // +/- 150 ns
`define RET     50000.0 // 50 us

module sams_tb;

localparam SKEWED = 1;
localparam NORMAL = 0;

reg serial_in =0;
wire [1:0] serial_out;
wire [23:0] data_out [1:0];
//***********************************************************************
//  Task to send bits normaly
//***********************************************************************
task send_bit;
    input bit_val;

begin
    if (bit_val) 
    begin
        serial_in = 1;
        #(`T1H);

        serial_in = 0;
        #(`T1L);
    end else 
    begin
        serial_in = 1;
        #(`T0H);

        serial_in = 0;
        #(`T0L);
        serial_in = 1;
    end
end
endtask
//***********************************************************************
//  Task to send bits with skew
//***********************************************************************
task send_bit_skewed;
    input bit_val;

begin
    if (bit_val) 
    begin
        serial_in = 1;
        #(`T1H - `MARGIN);

        serial_in = 0;
        #(`T1L - `MARGIN);
    end else 
    begin
        serial_in = 1;
        #(`T0H + `MARGIN);

        serial_in = 0;
        #(`T0L + `MARGIN);
        serial_in = 1;
    end
end
endtask
//***********************************************************************
// Task to send 24-bits; either normally or skewed
// if sel==1 send bytes in a skewed sequence
// if sel==0 send bytes in a normal sequence
//***********************************************************************
task send_bytes;
    integer i;
    input [23:0] bytes_to_send;
    input sel;

begin
    for (i = 23; i >= 0; i = i - 1) 
    begin
        if(~sel)
        send_bit(bytes_to_send[i]);
        else 
        send_bit_skewed(bytes_to_send[i]);
    end
end
endtask
//***********************************************************************
//  Task to display a special message
//***********************************************************************
task show_sacred_msg;
    integer j;
    reg [95:0] str1;
    begin
        str1 = "Xnt&qd^ghqdc";//coded message
    for (j = 0; j < 12; j = j+1) begin
        str1[8*j +: 8] = str1[8*j +: 8]+8'd1;
    end
    $display("%s", str1);
end
endtask


    // Instantiate the DUT
    led dut0(.i_serial(serial_in),
             .o_serial(serial_out[0]),
             .o_led(data_out[0]));

    // Instantiate the DUT
    led dut1(.i_serial(serial_out[0]),
             .o_serial(serial_out[1]),
             .o_led(data_out[1]));


    initial 
    begin 
        // Set up waveform output
        $dumpfile("sams_tb.vcd");
        $dumpvars(0, sams_tb);

        $display("Starting the test...");

        // Wait at least 50us to ensure reset completion
        #(`RET);
        $display("Reset LEDs");
        send_bytes(24'hF0F0FF, NORMAL);
        send_bytes(24'hF0F0FF, NORMAL);
        if (data_out[0] !== 24'hF0F0FF) $display("FAIL: LED1 output incorrect!");else show_sacred_msg();
        if (data_out[1] !== 24'hF0F0FF) $display("FAIL: LED2 output incorrect!");else show_sacred_msg();
        #(`RET);
        $display("Reset LEDs again");
        send_bytes(24'hF0F0FF, SKEWED);
        send_bytes(24'hF0F0FF, SKEWED);
        if (data_out[0] !== 24'hF0F0FF) $display("FAIL: LED1 output incorrect!"); else show_sacred_msg();
        if (data_out[1] !== 24'hF0F0FF) $display("FAIL: LED2 output incorrect!"); else show_sacred_msg();
        #1500; // Just kill a little time...
        $display("Ending the test...");

        $finish;
    end

endmodule

tb/sams_tb.vcd
$date
	Wed Jan 24 12:05:08 2024
$end
$version
	Icarus Verilog
$end
$timescale
	1ns
$end
$scope module sams_tb $end
$var wire 2 ! serial_out [1:0] $end
$var parameter 32 " NORMAL $end
$var parameter 32 # SKEWED $end
$var reg 1 $ serial_in $end
$scope module dut0 $end
$var wire 1 $ i_serial $end
$var wire 1 % o_serial $end
$var wire 24 & o_led [23:0] $end
$var parameter 32 ' CLK_PRD $end
$var parameter 10 ( RST_MIN $end
$var parameter 5 ) T0H_MAX $end
$var parameter 5 * T0H_MIN $end
$var parameter 5 + T1H_MAX $end
$var parameter 5 , T1H_MIN $end
$var parameter 2 - check $end
$var parameter 2 . idle $end
$var parameter 2 / measure $end
$var reg 5 0 bit_cntr [4:0] $end
$var reg 5 1 bit_timer [4:0] $end
$var reg 1 2 clk $end
$var reg 24 3 data [0:23] $end
$var reg 1 4 i_serial_sync $end
$var reg 1 5 i_serial_tmp $end
$var reg 10 6 rst_timer [9:0] $end
$var reg 2 7 state_nxt [1:0] $end
$var reg 2 8 state_reg [1:0] $end
$upscope $end
$scope module dut1 $end
$var wire 1 9 i_serial $end
$var wire 1 : o_serial $end
$var wire 24 ; o_led [23:0] $end
$var parameter 32 < CLK_PRD $end
$var parameter 10 = RST_MIN $end
$var parameter 5 > T0H_MAX $end
$var parameter 5 ? T0H_MIN $end
$var parameter 5 @ T1H_MAX $end
$var parameter 5 A T1H_MIN $end
$var parameter 2 B check $end
$var parameter 2 C idle $end
$var parameter 2 D measure $end
$var reg 5 E bit_cntr [4:0] $end
$var reg 5 F bit_timer [4:0] $end
$var reg 1 G clk $end
$var reg 24 H data [0:23] $end
$var reg 1 I i_serial_sync $end
$var reg 1 J i_serial_tmp $end
$var reg 10 K rst_timer [9:0] $end
$var reg 2 L state_nxt [1:0] $end
$var reg 2 M state_reg [1:0] $end
$upscope $end
$scope task send_bit $end
$var reg 1 N bit_val $end
$upscope $end
$scope task send_bit_skewed $end
$var reg 1 O bit_val $end
$upscope $end
$scope task send_bytes $end
$var reg 24 P bytes_to_send [23:0] $end
$var reg 1 Q sel $end
$var integer 32 R i [31:0] $end
$upscope $end
$scope task show_sacred_msg $end
$var reg 96 S str1 [95:0] $end
$var integer 32 T j [31:0] $end
$upscope $end
$upscope $end
$enddefinitions $end
$comment Show the parameter values. $end
$dumpall
b1 D
b0 C
b10 B
b1011 A
b10001 @
b100 ?
b1010 >
b1111101000 =
b110010 <
b1 /
b0 .
b10 -
b1011 ,
b10001 +
b100 *
b1010 )
b1111101000 (
b110010 '
b1 #
b0 "
$end
#0
$dumpvars
bx T
bx S
bx R
xQ
bx P
xO
xN
b0 M
b0 L
b0 K
0J
0I
b0 H
0G
b0 F
b0 E
b0 ;
0:
09
b0 8
b0 7
b0 6
05
04
b0 3
02
b0 1
b0 0
b0 &
0%
0$
b0 !
$end
#25
b1 K
b1 6
1G
12
#50
0G
02
#75
b10 K
b10 6
1G
12
#100
0G
02
#125
b11 K
b11 6
1G
12
#150
0G
02
#175
b100 K
b100 6
1G
12
#200
0G
02
#225
b101 K
b101 6
1G
12
#250
0G
02
#275
b110 K
b110 6
1G
12
#300
0G
02
#325
b111 K
b111 6
1G
12
#350
0G
02
#375
b1000 K
b1000 6
1G
12
#400
0G
02
#425
b1001 K
b1001 6
1G
12
#450
0G
02
#475
b1010 K
b1010 6
1G
12
#500
0G
02
#525
b1011 K
b1011 6
1G
12
#550
0G
02
#575
b1100 K
b1100 6
1G
12
#600
0G
02
#625
b1101 K
b1101 6
1G
12
#650
0G
02
#675
b1110 K
b1110 6
1G
12
#700
0G
02
#725
b1111 K
b1111 6
1G
12
#750
0G
02
#775
b10000 K
b10000 6
1G
12
#800
0G
02
#825
b10001 K
b10001 6
1G
12
#850
0G
02
#875
b10010 K
b10010 6
1G
12
#900
0G
02
#925
b10011 K
b10011 6
1G
12
#950
0G
02
#975
b10100 K
b10100 6
1G
12
#1000
0G
02
#1025
b10101 K
b10101 6
1G
12
#1050
0G
02
#1075
b10110 K
b10110 6
1G
12
#1100
0G
02
#1125
b10111 K
b10111 6
1G
12
#1150
0G
02
#1175
b11000 K
b11000 6
1G
12
#1200
0G
02
#1225
b11001 K
b11001 6
1G
12
#1250
0G
02
#1275
b11010 K
b11010 6
1G
12
#1300
0G
02
#1325
b11011 K
b11011 6
1G
12
#1350
0G
02
#1375
b11100 K
b11100 6
1G
12
#1400
0G
02
#1425
b11101 K
b11101 6
1G
12
#1450
0G
02
#1475
b11110 K
b11110 6
1G
12
#1500
0G
02
#1525
b11111 K
b11111 6
1G
12
#1550
0G
02
#1575
b100000 K
b100000 6
1G
12
#1600
0G
02
#1625
b100001 K
b100001 6
1G
12
#1650
0G
02
#1675
b100010 K
b100010 6
1G
12
#1700
0G
02
#1725
b100011 K
b100011 6
1G
12
#1750
0G
02
#1775
b100100 K
b100100 6
1G
12
#1800
0G
02
#1825
b100101 K
b100101 6
1G
12
#1850
0G
02
#1875
b100110 K
b100110 6
1G
12
#1900
0G
02
#1925
b100111 K
b100111 6
1G
12
#1950
0G
02
#1975
b101000 K
b101000 6
1G
12
#2000
0G
02
#2025
b101001 K
b101001 6
1G
12
#2050
0G
02
#2075
b101010 K
b101010 6
1G
12
#2100
0G
02
#2125
b101011 K
b101011 6
1G
12
#2150
0G
02
#2175
b101100 K
b101100 6
1G
12
#2200
0G
02
#2225
b101101 K
b101101 6
1G
12
#2250
0G
02
#2275
b101110 K
b101110 6
1G
12
#2300
0G
02
#2325
b101111 K
b101111 6
1G
12
#2350
0G
02
#2375
b110000 K
b110000 6
1G
12
#2400
0G
02
#2425
b110001 K
b110001 6
1G
12
#2450
0G
02
#2475
b110010 K
b110010 6
1G
12
#2500
0G
02
#2525
b110011 K
b110011 6
1G
12
#2550
0G
02
#2575
b110100 K
b110100 6
1G
12
#2600
0G
02
#2625
b110101 K
b110101 6
1G
12
#2650
0G
02
#2675
b110110 K
b110110 6
1G
12
#2700
0G
02
#2725
b110111 K
b110111 6
1G
12
#2750
0G
02
#2775
b111000 K
b111000 6
1G
12
#2800
0G
02
#2825
b111001 K
b111001 6
1G
12
#2850
0G
02
#2875
b111010 K
b111010 6
1G
12
#2900
0G
02
#2925
b111011 K
b111011 6
1G
12
#2950
0G
02
#2975
b111100 K
b111100 6
1G
12
#3000
0G
02
#3025
b111101 K
b111101 6
1G
12
#3050
0G
02
#3075
b111110 K
b111110 6
1G
12
#3100
0G
02
#3125
b111111 K
b111111 6
1G
12
#3150
0G
02
#3175
b1000000 K
b1000000 6
1G
12
#3200
0G
02
#3225
b1000001 K
b1000001 6
1G
12
#3250
0G
02
#3275
b1000010 K
b1000010 6
1G
12
#3300
0G
02
#3325
b1000011 K
b1000011 6
1G
12
#3350
0G
02
#3375
b1000100 K
b1000100 6
1G
12
#3400
0G
02
#3425
b1000101 K
b1000101 6
1G
12
#3450
0G
02
#3475
b1000110 K
b1000110 6
1G
12
#3500
0G
02
#3525
b1000111 K
b1000111 6
1G
12
#3550
0G
02
#3575
b1001000 K
b1001000 6
1G
12
#3600
0G
02
#3625
b1001001 K
b1001001 6
1G
12
#3650
0G
02
#3675
b1001010 K
b1001010 6
1G
12
#3700
0G
02
#3725
b1001011 K
b1001011 6
1G
12
#3750
0G
02
#3775
b1001100 K
b1001100 6
1G
12
#3800
0G
02
#3825
b1001101 K
b1001101 6
1G
12
#3850
0G
02
#3875
b1001110 K
b1001110 6
1G
12
#3900
0G
02
#3925
b1001111 K
b1001111 6
1G
12
#3950
0G
02
#3975
b1010000 K
b1010000 6
1G
12
#4000
0G
02
#4025
b1010001 K
b1010001 6
1G
12
#4050
0G
02
#4075
b1010010 K
b1010010 6
1G
12
#4100
0G
02
#4125
b1010011 K
b1010011 6
1G
12
#4150
0G
02
#4175
b1010100 K
b1010100 6
1G
12
#4200
0G
02
#4225
b1010101 K
b1010101 6
1G
12
#4250
0G
02
#4275
b1010110 K
b1010110 6
1G
12
#4300
0G
02
#4325
b1010111 K
b1010111 6
1G
12
#4350
0G
02
#4375
b1011000 K
b1011000 6
1G
12
#4400
0G
02
#4425
b1011001 K
b1011001 6
1G
12
#4450
0G
02
#4475
b1011010 K
b1011010 6
1G
12
#4500
0G
02
#4525
b1011011 K
b1011011 6
1G
12
#4550
0G
02
#4575
b1011100 K
b1011100 6
1G
12
#4600
0G
02
#4625
b1011101 K
b1011101 6
1G
12
#4650
0G
02
#4675
b1011110 K
b1011110 6
1G
12
#4700
0G
02
#4725
b1011111 K
b1011111 6
1G
12
#4750
0G
02
#4775
b1100000 K
b1100000 6
1G
12
#4800
0G
02
#4825
b1100001 K
b1100001 6
1G
12
#4850
0G
02
#4875
b1100010 K
b1100010 6
1G
12
#4900
0G
02
#4925
b1100011 K
b1100011 6
1G
12
#4950
0G
02
#4975
b1100100 K
b1100100 6
1G
12
#5000
0G
02
#5025
b1100101 K
b1100101 6
1G
12
#5050
0G
02
#5075
b1100110 K
b1100110 6
1G
12
#5100
0G
02
#5125
b1100111 K
b1100111 6
1G
12
#5150
0G
02
#5175
b1101000 K
b1101000 6
1G
12
#5200
0G
02
#5225
b1101001 K
b1101001 6
1G
12
#5250
0G
02
#5275
b1101010 K
b1101010 6
1G
12
#5300
0G
02
#5325
b1101011 K
b1101011 6
1G
12
#5350
0G
02
#5375
b1101100 K
b1101100 6
1G
12
#5400
0G
02
#5425
b1101101 K
b1101101 6
1G
12
#5450
0G
02
#5475
b1101110 K
b1101110 6
1G
12
#5500
0G
02
#5525
b1101111 K
b1101111 6
1G
12
#5550
0G
02
#5575
b1110000 K
b1110000 6
1G
12
#5600
0G
02
#5625
b1110001 K
b1110001 6
1G
12
#5650
0G
02
#5675
b1110010 K
b1110010 6
1G
12
#5700
0G
02
#5725
b1110011 K
b1110011 6
1G
12
#5750
0G
02
#5775
b1110100 K
b1110100 6
1G
12
#5800
0G
02
#5825
b1110101 K
b1110101 6
1G
12
#5850
0G
02
#5875
b1110110 K
b1110110 6
1G
12
#5900
0G
02
#5925
b1110111 K
b1110111 6
1G
12
#5950
0G
02
#5975
b1111000 K
b1111000 6
1G
12
#6000
0G
02
#6025
b1111001 K
b1111001 6
1G
12
#6050
0G
02
#6075
b1111010 K
b1111010 6
1G
12
#6100
0G
02
#6125
b1111011 K
b1111011 6
1G
12
#6150
0G
02
#6175
b1111100 K
b1111100 6
1G
12
#6200
0G
02
#6225
b1111101 K
b1111101 6
1G
12
#6250
0G
02
#6275
b1111110 K
b1111110 6
1G
12
#6300
0G
02
#6325
b1111111 K
b1111111 6
1G
12
#6350
0G
02
#6375
b10000000 K
b10000000 6
1G
12
#6400
0G
02
#6425
b10000001 K
b10000001 6
1G
12
#6450
0G
02
#6475
b10000010 K
b10000010 6
1G
12
#6500
0G
02
#6525
b10000011 K
b10000011 6
1G
12
#6550
0G
02
#6575
b10000100 K
b10000100 6
1G
12
#6600
0G
02
#6625
b10000101 K
b10000101 6
1G
12
#6650
0G
02
#6675
b10000110 K
b10000110 6
1G
12
#6700
0G
02
#6725
b10000111 K
b10000111 6
1G
12
#6750
0G
02
#6775
b10001000 K
b10001000 6
1G
12
#6800
0G
02
#6825
b10001001 K
b10001001 6
1G
12
#6850
0G
02
#6875
b10001010 K
b10001010 6
1G
12
#6900
0G
02
#6925
b10001011 K
b10001011 6
1G
12
#6950
0G
02
#6975
b10001100 K
b10001100 6
1G
12
#7000
0G
02
#7025
b10001101 K
b10001101 6
1G
12
#7050
0G
02
#7075
b10001110 K
b10001110 6
1G
12
#7100
0G
02
#7125
b10001111 K
b10001111 6
1G
12
#7150
0G
02
#7175
b10010000 K
b10010000 6
1G
12
#7200
0G
02
#7225
b10010001 K
b10010001 6
1G
12
#7250
0G
02
#7275
b10010010 K
b10010010 6
1G
12
#7300
0G
02
#7325
b10010011 K
b10010011 6
1G
12
#7350
0G
02
#7375
b10010100 K
b10010100 6
1G
12
#7400
0G
02
#7425
b10010101 K
b10010101 6
1G
12
#7450
0G
02
#7475
b10010110 K
b10010110 6
1G
12
#7500
0G
02
#7525
b10010111 K
b10010111 6
1G
12
#7550
0G
02
#7575
b10011000 K
b10011000 6
1G
12
#7600
0G
02
#7625
b10011001 K
b10011001 6
1G
12
#7650
0G
02
#7675
b10011010 K
b10011010 6
1G
12
#7700
0G
02
#7725
b10011011 K
b10011011 6
1G
12
#7750
0G
02
#7775
b10011100 K
b10011100 6
1G
12
#7800
0G
02
#7825
b10011101 K
b10011101 6
1G
12
#7850
0G
02
#7875
b10011110 K
b10011110 6
1G
12
#7900
0G
02
#7925
b10011111 K
b10011111 6
1G
12
#7950
0G
02
#7975
b10100000 K
b10100000 6
1G
12
#8000
0G
02
#8025
b10100001 K
b10100001 6
1G
12
#8050
0G
02
#8075
b10100010 K
b10100010 6
1G
12
#8100
0G
02
#8125
b10100011 K
b10100011 6
1G
12
#8150
0G
02
#8175
b10100100 K
b10100100 6
1G
12
#8200
0G
02
#8225
b10100101 K
b10100101 6
1G
12
#8250
0G
02
#8275
b10100110 K
b10100110 6
1G
12
#8300
0G
02
#8325
b10100111 K
b10100111 6
1G
12
#8350
0G
02
#8375
b10101000 K
b10101000 6
1G
12
#8400
0G
02
#8425
b10101001 K
b10101001 6
1G
12
#8450
0G
02
#8475
b10101010 K
b10101010 6
1G
12
#8500
0G
02
#8525
b10101011 K
b10101011 6
1G
12
#8550
0G
02
#8575
b10101100 K
b10101100 6
1G
12
#8600
0G
02
#8625
b10101101 K
b10101101 6
1G
12
#8650
0G
02
#8675
b10101110 K
b10101110 6
1G
12
#8700
0G
02
#8725
b10101111 K
b10101111 6
1G
12
#8750
0G
02
#8775
b10110000 K
b10110000 6
1G
12
#8800
0G
02
#8825
b10110001 K
b10110001 6
1G
12
#8850
0G
02
#8875
b10110010 K
b10110010 6
1G
12
#8900
0G
02
#8925
b10110011 K
b10110011 6
1G
12
#8950
0G
02
#8975
b10110100 K
b10110100 6
1G
12
#9000
0G
02
#9025
b10110101 K
b10110101 6
1G
12
#9050
0G
02
#9075
b10110110 K
b10110110 6
1G
12
#9100
0G
02
#9125
b10110111 K
b10110111 6
1G
12
#9150
0G
02
#9175
b10111000 K
b10111000 6
1G
12
#9200
0G
02
#9225
b10111001 K
b10111001 6
1G
12
#9250
0G
02
#9275
b10111010 K
b10111010 6
1G
12
#9300
0G
02
#9325
b10111011 K
b10111011 6
1G
12
#9350
0G
02
#9375
b10111100 K
b10111100 6
1G
12
#9400
0G
02
#9425
b10111101 K
b10111101 6
1G
12
#9450
0G
02
#9475
b10111110 K
b10111110 6
1G
12
#9500
0G
02
#9525
b10111111 K
b10111111 6
1G
12
#9550
0G
02
#9575
b11000000 K
b11000000 6
1G
12
#9600
0G
02
#9625
b11000001 K
b11000001 6
1G
12
#9650
0G
02
#9675
b11000010 K
b11000010 6
1G
12
#9700
0G
02
#9725
b11000011 K
b11000011 6
1G
12
#9750
0G
02
#9775
b11000100 K
b11000100 6
1G
12
#9800
0G
02
#9825
b11000101 K
b11000101 6
1G
12
#9850
0G
02
#9875
b11000110 K
b11000110 6
1G
12
#9900
0G
02
#9925
b11000111 K
b11000111 6
1G
12
#9950
0G
02
#9975
b11001000 K
b11001000 6
1G
12
#10000
0G
02
#10025
b11001001 K
b11001001 6
1G
12
#10050
0G
02
#10075
b11001010 K
b11001010 6
1G
12
#10100
0G
02
#10125
b11001011 K
b11001011 6
1G
12
#10150
0G
02
#10175
b11001100 K
b11001100 6
1G
12
#10200
0G
02
#10225
b11001101 K
b11001101 6
1G
12
#10250
0G
02
#10275
b11001110 K
b11001110 6
1G
12
#10300
0G
02
#10325
b11001111 K
b11001111 6
1G
12
#10350
0G
02
#10375
b11010000 K
b11010000 6
1G
12
#10400
0G
02
#10425
b11010001 K
b11010001 6
1G
12
#10450
0G
02
#10475
b11010010 K
b11010010 6
1G
12
#10500
0G
02
#10525
b11010011 K
b11010011 6
1G
12
#10550
0G
02
#10575
b11010100 K
b11010100 6
1G
12
#10600
0G
02
#10625
b11010101 K
b11010101 6
1G
12
#10650
0G
02
#10675
b11010110 K
b11010110 6
1G
12
#10700
0G
02
#10725
b11010111 K
b11010111 6
1G
12
#10750
0G
02
#10775
b11011000 K
b11011000 6
1G
12
#10800
0G
02
#10825
b11011001 K
b11011001 6
1G
12
#10850
0G
02
#10875
b11011010 K
b11011010 6
1G
12
#10900
0G
02
#10925
b11011011 K
b11011011 6
1G
12
#10950
0G
02
#10975
b11011100 K
b11011100 6
1G
12
#11000
0G
02
#11025
b11011101 K
b11011101 6
1G
12
#11050
0G
02
#11075
b11011110 K
b11011110 6
1G
12
#11100
0G
02
#11125
b11011111 K
b11011111 6
1G
12
#11150
0G
02
#11175
b11100000 K
b11100000 6
1G
12
#11200
0G
02
#11225
b11100001 K
b11100001 6
1G
12
#11250
0G
02
#11275
b11100010 K
b11100010 6
1G
12
#11300
0G
02
#11325
b11100011 K
b11100011 6
1G
12
#11350
0G
02
#11375
b11100100 K
b11100100 6
1G
12
#11400
0G
02
#11425
b11100101 K
b11100101 6
1G
12
#11450
0G
02
#11475
b11100110 K
b11100110 6
1G
12
#11500
0G
02
#11525
b11100111 K
b11100111 6
1G
12
#11550
0G
02
#11575
b11101000 K
b11101000 6
1G
12
#11600
0G
02
#11625
b11101001 K
b11101001 6
1G
12
#11650
0G
02
#11675
b11101010 K
b11101010 6
1G
12
#11700
0G
02
#11725
b11101011 K
b11101011 6
1G
12
#11750
0G
02
#11775
b11101100 K
b11101100 6
1G
12
#11800
0G
02
#11825
b11101101 K
b11101101 6
1G
12
#11850
0G
02
#11875
b11101110 K
b11101110 6
1G
12
#11900
0G
02
#11925
b11101111 K
b11101111 6
1G
12
#11950
0G
02
#11975
b11110000 K
b11110000 6
1G
12
#12000
0G
02
#12025
b11110001 K
b11110001 6
1G
12
#12050
0G
02
#12075
b11110010 K
b11110010 6
1G
12
#12100
0G
02
#12125
b11110011 K
b11110011 6
1G
12
#12150
0G
02
#12175
b11110100 K
b11110100 6
1G
12
#12200
0G
02
#12225
b11110101 K
b11110101 6
1G
12
#12250
0G
02
#12275
b11110110 K
b11110110 6
1G
12
#12300
0G
02
#12325
b11110111 K
b11110111 6
1G
12
#12350
0G
02
#12375
b11111000 K
b11111000 6
1G
12
#12400
0G
02
#12425
b11111001 K
b11111001 6
1G
12
#12450
0G
02
#12475
b11111010 K
b11111010 6
1G
12
#12500
0G
02
#12525
b11111011 K
b11111011 6
1G
12
#12550
0G
02
#12575
b11111100 K
b11111100 6
1G
12
#12600
0G
02
#12625
b11111101 K
b11111101 6
1G
12
#12650
0G
02
#12675
b11111110 K
b11111110 6
1G
12
#12700
0G
02
#12725
b11111111 K
b11111111 6
1G
12
#12750
0G
02
#12775
b100000000 K
b100000000 6
1G
12
#12800
0G
02
#12825
b100000001 K
b100000001 6
1G
12
#12850
0G
02
#12875
b100000010 K
b100000010 6
1G
12
#12900
0G
02
#12925
b100000011 K
b100000011 6
1G
12
#12950
0G
02
#12975
b100000100 K
b100000100 6
1G
12
#13000
0G
02
#13025
b100000101 K
b100000101 6
1G
12
#13050
0G
02
#13075
b100000110 K
b100000110 6
1G
12
#13100
0G
02
#13125
b100000111 K
b100000111 6
1G
12
#13150
0G
02
#13175
b100001000 K
b100001000 6
1G
12
#13200
0G
02
#13225
b100001001 K
b100001001 6
1G
12
#13250
0G
02
#13275
b100001010 K
b100001010 6
1G
12
#13300
0G
02
#13325
b100001011 K
b100001011 6
1G
12
#13350
0G
02
#13375
b100001100 K
b100001100 6
1G
12
#13400
0G
02
#13425
b100001101 K
b100001101 6
1G
12
#13450
0G
02
#13475
b100001110 K
b100001110 6
1G
12
#13500
0G
02
#13525
b100001111 K
b100001111 6
1G
12
#13550
0G
02
#13575
b100010000 K
b100010000 6
1G
12
#13600
0G
02
#13625
b100010001 K
b100010001 6
1G
12
#13650
0G
02
#13675
b100010010 K
b100010010 6
1G
12
#13700
0G
02
#13725
b100010011 K
b100010011 6
1G
12
#13750
0G
02
#13775
b100010100 K
b100010100 6
1G
12
#13800
0G
02
#13825
b100010101 K
b100010101 6
1G
12
#13850
0G
02
#13875
b100010110 K
b100010110 6
1G
12
#13900
0G
02
#13925
b100010111 K
b100010111 6
1G
12
#13950
0G
02
#13975
b100011000 K
b100011000 6
1G
12
#14000
0G
02
#14025
b100011001 K
b100011001 6
1G
12
#14050
0G
02
#14075
b100011010 K
b100011010 6
1G
12
#14100
0G
02
#14125
b100011011 K
b100011011 6
1G
12
#14150
0G
02
#14175
b100011100 K
b100011100 6
1G
12
#14200
0G
02
#14225
b100011101 K
b100011101 6
1G
12
#14250
0G
02
#14275
b100011110 K
b100011110 6
1G
12
#14300
0G
02
#14325
b100011111 K
b100011111 6
1G
12
#14350
0G
02
#14375
b100100000 K
b100100000 6
1G
12
#14400
0G
02
#14425
b100100001 K
b100100001 6
1G
12
#14450
0G
02
#14475
b100100010 K
b100100010 6
1G
12
#14500
0G
02
#14525
b100100011 K
b100100011 6
1G
12
#14550
0G
02
#14575
b100100100 K
b100100100 6
1G
12
#14600
0G
02
#14625
b100100101 K
b100100101 6
1G
12
#14650
0G
02
#14675
b100100110 K
b100100110 6
1G
12
#14700
0G
02
#14725
b100100111 K
b100100111 6
1G
12
#14750
0G
02
#14775
b100101000 K
b100101000 6
1G
12
#14800
0G
02
#14825
b100101001 K
b100101001 6
1G
12
#14850
0G
02
#14875
b100101010 K
b100101010 6
1G
12
#14900
0G
02
#14925
b100101011 K
b100101011 6
1G
12
#14950
0G
02
#14975
b100101100 K
b100101100 6
1G
12
#15000
0G
02
#15025
b100101101 K
b100101101 6
1G
12
#15050
0G
02
#15075
b100101110 K
b100101110 6
1G
12
#15100
0G
02
#15125
b100101111 K
b100101111 6
1G
12
#15150
0G
02
#15175
b100110000 K
b100110000 6
1G
12
#15200
0G
02
#15225
b100110001 K
b100110001 6
1G
12
#15250
0G
02
#15275
b100110010 K
b100110010 6
1G
12
#15300
0G
02
#15325
b100110011 K
b100110011 6
1G
12
#15350
0G
02
#15375
b100110100 K
b100110100 6
1G
12
#15400
0G
02
#15425
b100110101 K
b100110101 6
1G
12
#15450
0G
02
#15475
b100110110 K
b100110110 6
1G
12
#15500
0G
02
#15525
b100110111 K
b100110111 6
1G
12
#15550
0G
02
#15575
b100111000 K
b100111000 6
1G
12
#15600
0G
02
#15625
b100111001 K
b100111001 6
1G
12
#15650
0G
02
#15675
b100111010 K
b100111010 6
1G
12
#15700
0G
02
#15725
b100111011 K
b100111011 6
1G
12
#15750
0G
02
#15775
b100111100 K
b100111100 6
1G
12
#15800
0G
02
#15825
b100111101 K
b100111101 6
1G
12
#15850
0G
02
#15875
b100111110 K
b100111110 6
1G
12
#15900
0G
02
#15925
b100111111 K
b100111111 6
1G
12
#15950
0G
02
#15975
b101000000 K
b101000000 6
1G
12
#16000
0G
02
#16025
b101000001 K
b101000001 6
1G
12
#16050
0G
02
#16075
b101000010 K
b101000010 6
1G
12
#16100
0G
02
#16125
b101000011 K
b101000011 6
1G
12
#16150
0G
02
#16175
b101000100 K
b101000100 6
1G
12
#16200
0G
02
#16225
b101000101 K
b101000101 6
1G
12
#16250
0G
02
#16275
b101000110 K
b101000110 6
1G
12
#16300
0G
02
#16325
b101000111 K
b101000111 6
1G
12
#16350
0G
02
#16375
b101001000 K
b101001000 6
1G
12
#16400
0G
02
#16425
b101001001 K
b101001001 6
1G
12
#16450
0G
02
#16475
b101001010 K
b101001010 6
1G
12
#16500
0G
02
#16525
b101001011 K
b101001011 6
1G
12
#16550
0G
02
